[{"type":"shapeless","itemId":"minecraft:suspicious_stew","count":1,"recipe":{"items":["minecraft:bowl","minecraft:brown_mushroom","minecraft:red_mushroom","minecraft:allium"]}},{"type":"shapeless","itemId":"minecraft:suspicious_stew","count":1,"recipe":{"items":["minecraft:bowl","minecraft:brown_mushroom","minecraft:red_mushroom","minecraft:azure_bluet"]}},{"type":"shapeless","itemId":"minecraft:suspicious_stew","count":1,"recipe":{"items":["minecraft:bowl","minecraft:brown_mushroom","minecraft:red_mushroom","minecraft:blue_orchid"]}},{"type":"shapeless","itemId":"minecraft:suspicious_stew","count":1,"recipe":{"items":["minecraft:bowl","minecraft:brown_mushroom","minecraft:red_mushroom","minecraft:closed_eyeblossom"]}},{"type":"shapeless","itemId":"minecraft:suspicious_stew","count":1,"recipe":{"items":["minecraft:bowl","minecraft:brown_mushroom","minecraft:red_mushroom","minecraft:cornflower"]}},{"type":"shapeless","itemId":"minecraft:suspicious_stew","count":1,"recipe":{"items":["minecraft:bowl","minecraft:brown_mushroom","minecraft:red_mushroom","minecraft:dandelion"]}},{"type":"shapeless","itemId":"minecraft:suspicious_stew","count":1,"recipe":{"items":["minecraft:bowl","minecraft:brown_mushroom","minecraft:red_mushroom","minecraft:lily_of_the_valley"]}},{"type":"shapeless","itemId":"minecraft:suspicious_stew","count":1,"recipe":{"items":["minecraft:bowl","minecraft:brown_mushroom","minecraft:red_mushroom","minecraft:open_eyeblossom"]}},{"type":"shapeless","itemId":"minecraft:suspicious_stew","count":1,"recipe":{"items":["minecraft:bowl","minecraft:brown_mushroom","minecraft:red_mushroom","minecraft:orange_tulip"]}},{"type":"shapeless","itemId":"minecraft:suspicious_stew","count":1,"recipe":{"items":["minecraft:bowl","minecraft:brown_mushroom","minecraft:red_mushroom","minecraft:oxeye_daisy"]}},{"type":"shapeless","itemId":"minecraft:suspicious_stew","count":1,"recipe":{"items":["minecraft:bowl","minecraft:brown_mushroom","minecraft:red_mushroom","minecraft:pink_tulip"]}},{"type":"shapeless","itemId":"minecraft:suspicious_stew","count":1,"recipe":{"items":["minecraft:bowl","minecraft:brown_mushroom","minecraft:red_mushroom","minecraft:poppy"]}},{"type":"shapeless","itemId":"minecraft:suspicious_stew","count":1,"recipe":{"items":["minecraft:bowl","minecraft:brown_mushroom","minecraft:red_mushroom","minecraft:red_tulip"]}},{"type":"shapeless","itemId":"minecraft:suspicious_stew","count":1,"recipe":{"items":["minecraft:bowl","minecraft:brown_mushroom","minecraft:red_mushroom","minecraft:torchflower"]}},{"type":"shapeless","itemId":"minecraft:suspicious_stew","count":1,"recipe":{"items":["minecraft:bowl","minecraft:brown_mushroom","minecraft:red_mushroom","minecraft:white_tulip"]}},{"type":"shapeless","itemId":"minecraft:suspicious_stew","count":1,"recipe":{"items":["minecraft:bowl","minecraft:brown_mushroom","minecraft:red_mushroom","minecraft:wither_rose"]}}]